ccres_weather_station/__init__.py
ccres_weather_station/ccres_weather_station.py
ccres_weather_station/logger.py
ccres_weather_station/types.py
ccres_weather_station/bounders/apply_bounds.py
ccres_weather_station/cli/cli.py
ccres_weather_station/config/config.py
ccres_weather_station/readers/__init__.py
ccres_weather_station/readers/base.py
ccres_weather_station/readers/constants.py
ccres_weather_station/readers/register.py
ccres_weather_station/readers/sirta.py
ccres_weather_station/writers/write.py
ccres_weather_station-0.1.0.dev2.dist-info/LICENSE
ccres_weather_station-0.1.0.dev2.dist-info/METADATA
ccres_weather_station-0.1.0.dev2.dist-info/WHEEL
ccres_weather_station-0.1.0.dev2.dist-info/entry_points.txt
ccres_weather_station-0.1.0.dev2.dist-info/top_level.txt
ccres_weather_station-0.1.0.dev2.dist-info/RECORD
