Metadata-Version: 2.1
Name: ccres-weather-station
Version: 0.1.0.dev2
Summary: CCRES codes to convert weather data from text files to NetCDF files
Author-email: ACTRIS-CCRES <ccres-dev@listes.ipsl.fr>
License: GNU AFFERO GENERAL PUBLIC LICENSE
Project-URL: homepage, https://github.com/ACTRIS-CCRES/ccres-weather-station
Project-URL: documentation, https://ccres-weather-station.readthedocs.io/en/latest/?version=latest
Project-URL: repository, https://github.com/ACTRIS-CCRES/ccres-weather-station
Project-URL: changelog, https://github.com/ACTRIS-CCRES/ccres-weather-station/blob/main/CHANGELOG.md
Project-URL: Bug Tracker, https://github.com/ACTRIS-CCRES/ccres-weather-station/issues
Keywords: ccres_weather_station
Classifier: Development Status :: 2 - Pre-Alpha
Classifier: Intended Audience :: Developers
Classifier: License :: OSI Approved :: GNU Affero General Public License v3
Classifier: Natural Language :: English
Classifier: Programming Language :: Python :: Implementation :: CPython
Classifier: Programming Language :: Python :: 3
Classifier: Programming Language :: Python :: 3.8
Classifier: Programming Language :: Python :: 3.9
Classifier: Programming Language :: Python :: 3.10
Classifier: Programming Language :: Python :: 3.11
Requires-Python: >=3.8
License-File: LICENSE
Requires-Dist: click
Requires-Dist: xarray
Requires-Dist: numpy (>=1.2)
Requires-Dist: pandas (>=1.4)
Requires-Dist: netCDF4
Requires-Dist: toml
Requires-Dist: GitPython
Provides-Extra: dev
Requires-Dist: ccres-weather-station ; extra == 'dev'
Requires-Dist: pytest (>=6.1.1) ; extra == 'dev'
Requires-Dist: pytest-cov (>=2.10.1) ; extra == 'dev'
Requires-Dist: pytest-mock (>=3.6.1) ; extra == 'dev'
Requires-Dist: coverage (>=5.3) ; extra == 'dev'
Requires-Dist: sphinx (>=4.5.0) ; extra == 'dev'
Requires-Dist: myst ; extra == 'dev'
Requires-Dist: myst-parser ; extra == 'dev'
Requires-Dist: sphinx-book-theme (>=0.3.0) ; extra == 'dev'
Requires-Dist: tox ; extra == 'dev'
Requires-Dist: pre-commit ; extra == 'dev'
Requires-Dist: bump2version ; extra == 'dev'
Requires-Dist: black ; extra == 'dev'
Requires-Dist: flake8 ; extra == 'dev'
Requires-Dist: mypy ; extra == 'dev'
